{
  "forgeVersion": "0.2.0",
  "runs": [
    {
      "taskId": "C3",
      "createdAt": "2026-06-06T11:28:35.723+08:00",
      "complexity": "complex",
      "completedInFirstAttempt": false,
      "wrongFileModified": false,
      "unrelatedCodeChanged": false,
      "changedFiles": [
        "src/renderer/src/App.tsx",
        "src/renderer/src/agent/failureRecoveryMetrics.ts",
        "tests/failureRecoveryMetrics.test.ts"
      ],
      "validations": [
        {
          "kind": "typecheck",
          "command": "npm run typecheck",
          "exitCode": 0,
          "passed": true,
          "afterModification": true
        },
        {
          "kind": "build",
          "command": "npm run build",
          "exitCode": 0,
          "passed": true,
          "afterModification": true
        },
        {
          "kind": "lint",
          "command": "npm run lint",
          "exitCode": 0,
          "passed": true,
          "afterModification": true
        }
      ],
      "failureRecovered": true
    },
    {
      "taskId": "C2",
      "createdAt": "2026-06-06T11:36:50.238+08:00",
      "complexity": "complex",
      "completedInFirstAttempt": true,
      "wrongFileModified": false,
      "unrelatedCodeChanged": false,
      "changedFiles": [
        "tests/agentQualityMetricsLog.test.ts"
      ],
      "validations": [
        {
          "kind": "typecheck",
          "command": "npm run typecheck",
          "exitCode": 0,
          "passed": true,
          "afterModification": true
        },
        {
          "kind": "build",
          "command": "npm run build",
          "exitCode": 0,
          "passed": true,
          "afterModification": true
        },
        {
          "kind": "lint",
          "command": "npm run lint",
          "exitCode": 0,
          "passed": true,
          "afterModification": true
        }
      ],
      "failureRecovered": null
    },
    {
      "taskId": "C1",
      "createdAt": "2026-06-06T11:43:44.578+08:00",
      "complexity": "complex",
      "completedInFirstAttempt": true,
      "wrongFileModified": false,
      "unrelatedCodeChanged": false,
      "changedFiles": [
        "scripts/run-v0-2-quality-gate.mjs"
      ],
      "validations": [
        {
          "kind": "typecheck",
          "command": "npm run typecheck",
          "exitCode": 0,
          "passed": true,
          "afterModification": true
        },
        {
          "kind": "build",
          "command": "npm run build",
          "exitCode": 0,
          "passed": true,
          "afterModification": true
        },
        {
          "kind": "lint",
          "command": "npm run lint",
          "exitCode": 0,
          "passed": true,
          "afterModification": true
        }
      ],
      "failureRecovered": null
    },
    {
      "taskId": "S2",
      "createdAt": "2026-06-06T11:48:31.312+08:00",
      "complexity": "simple",
      "completedInFirstAttempt": true,
      "wrongFileModified": false,
      "unrelatedCodeChanged": false,
      "changedFiles": [
        "docs/RELEASE.md"
      ],
      "validations": [
        {
          "kind": "typecheck",
          "command": "npm run typecheck",
          "exitCode": 0,
          "passed": true,
          "afterModification": true
        },
        {
          "kind": "build",
          "command": "npm run build",
          "exitCode": 0,
          "passed": true,
          "afterModification": true
        },
        {
          "kind": "lint",
          "command": "npm run lint",
          "exitCode": 0,
          "passed": true,
          "afterModification": true
        }
      ],
      "failureRecovered": null
    },
    {
      "taskId": "S1",
      "createdAt": "2026-06-06T11:55:27.663+08:00",
      "complexity": "simple",
      "completedInFirstAttempt": true,
      "wrongFileModified": false,
      "unrelatedCodeChanged": false,
      "changedFiles": [
        "README.md",
        "README.en.md"
      ],
      "validations": [
        {
          "kind": "typecheck",
          "command": "npm run typecheck",
          "exitCode": 0,
          "passed": true,
          "afterModification": true
        },
        {
          "kind": "build",
          "command": "npm run build",
          "exitCode": 0,
          "passed": true,
          "afterModification": true
        },
        {
          "kind": "lint",
          "command": "npm run lint",
          "exitCode": 0,
          "passed": true,
          "afterModification": true
        }
      ],
      "failureRecovered": null
    },
    {
      "taskId": "S3",
      "createdAt": "2026-06-06T11:55:27.663+08:00",
      "complexity": "simple",
      "completedInFirstAttempt": true,
      "wrongFileModified": false,
      "unrelatedCodeChanged": false,
      "changedFiles": [
        "README.md",
        "README.en.md"
      ],
      "validations": [
        {
          "kind": "typecheck",
          "command": "npm run typecheck",
          "exitCode": 0,
          "passed": true,
          "afterModification": true
        },
        {
          "kind": "build",
          "command": "npm run build",
          "exitCode": 0,
          "passed": true,
          "afterModification": true
        },
        {
          "kind": "lint",
          "command": "npm run lint",
          "exitCode": 0,
          "passed": true,
          "afterModification": true
        }
      ],
      "failureRecovered": null
    },
    {
      "taskId": "S5",
      "createdAt": "2026-06-06T11:55:27.663+08:00",
      "complexity": "simple",
      "completedInFirstAttempt": true,
      "wrongFileModified": false,
      "unrelatedCodeChanged": false,
      "changedFiles": [
        "README.md",
        "README.en.md"
      ],
      "validations": [
        {
          "kind": "typecheck",
          "command": "npm run typecheck",
          "exitCode": 0,
          "passed": true,
          "afterModification": true
        },
        {
          "kind": "build",
          "command": "npm run build",
          "exitCode": 0,
          "passed": true,
          "afterModification": true
        },
        {
          "kind": "lint",
          "command": "npm run lint",
          "exitCode": 0,
          "passed": true,
          "afterModification": true
        }
      ],
      "failureRecovered": null
    },
    {
      "taskId": "S4",
      "createdAt": "2026-06-06T12:04:09.853+08:00",
      "complexity": "simple",
      "completedInFirstAttempt": true,
      "wrongFileModified": false,
      "unrelatedCodeChanged": false,
      "changedFiles": [
        "docs/superpowers/plans/2026-06-05-v0-2-stabilization.md"
      ],
      "validations": [
        {
          "kind": "typecheck",
          "command": "npm run typecheck",
          "exitCode": 0,
          "passed": true,
          "afterModification": true
        },
        {
          "kind": "build",
          "command": "npm run build",
          "exitCode": 0,
          "passed": true,
          "afterModification": true
        },
        {
          "kind": "lint",
          "command": "npm run lint",
          "exitCode": 0,
          "passed": true,
          "afterModification": true
        }
      ],
      "failureRecovered": null
    },
    {
      "taskId": "M1",
      "createdAt": "2026-06-06T12:04:09.853+08:00",
      "complexity": "medium",
      "completedInFirstAttempt": true,
      "wrongFileModified": false,
      "unrelatedCodeChanged": false,
      "changedFiles": [
        "tests/agentQualityMetrics.test.ts"
      ],
      "validations": [
        {
          "kind": "typecheck",
          "command": "npm run typecheck",
          "exitCode": 0,
          "passed": true,
          "afterModification": true
        },
        {
          "kind": "build",
          "command": "npm run build",
          "exitCode": 0,
          "passed": true,
          "afterModification": true
        },
        {
          "kind": "lint",
          "command": "npm run lint",
          "exitCode": 0,
          "passed": true,
          "afterModification": true
        }
      ],
      "failureRecovered": null
    },
    {
      "taskId": "M2",
      "createdAt": "2026-06-06T12:04:09.853+08:00",
      "complexity": "medium",
      "completedInFirstAttempt": true,
      "wrongFileModified": false,
      "unrelatedCodeChanged": false,
      "changedFiles": [
        "tests/agentQualityMetrics.test.ts"
      ],
      "validations": [
        {
          "kind": "typecheck",
          "command": "npm run typecheck",
          "exitCode": 0,
          "passed": true,
          "afterModification": true
        },
        {
          "kind": "build",
          "command": "npm run build",
          "exitCode": 0,
          "passed": true,
          "afterModification": true
        },
        {
          "kind": "lint",
          "command": "npm run lint",
          "exitCode": 0,
          "passed": true,
          "afterModification": true
        }
      ],
      "failureRecovered": null
    },
    {
      "taskId": "M3",
      "createdAt": "2026-06-06T12:13:28.372+08:00",
      "complexity": "medium",
      "completedInFirstAttempt": true,
      "wrongFileModified": false,
      "unrelatedCodeChanged": false,
      "changedFiles": [
        "README.en.md",
        "docs/RELEASE.md",
        "docs/superpowers/plans/2026-06-05-v0-2-stabilization.md"
      ],
      "validations": [
        {
          "kind": "typecheck",
          "command": "npm run typecheck",
          "exitCode": 0,
          "passed": true,
          "afterModification": true
        },
        {
          "kind": "build",
          "command": "npm run build",
          "exitCode": 0,
          "passed": true,
          "afterModification": true
        },
        {
          "kind": "lint",
          "command": "npm run lint",
          "exitCode": 0,
          "passed": true,
          "afterModification": true
        }
      ],
      "failureRecovered": null
    },
    {
      "taskId": "M4",
      "createdAt": "2026-06-06T12:13:28.372+08:00",
      "complexity": "medium",
      "completedInFirstAttempt": true,
      "wrongFileModified": false,
      "unrelatedCodeChanged": false,
      "changedFiles": [
        "docs/RELEASE.md",
        "docs/superpowers/plans/2026-06-05-v0-2-stabilization.md"
      ],
      "validations": [
        {
          "kind": "typecheck",
          "command": "npm run typecheck",
          "exitCode": 0,
          "passed": true,
          "afterModification": true
        },
        {
          "kind": "build",
          "command": "npm run build",
          "exitCode": 0,
          "passed": true,
          "afterModification": true
        },
        {
          "kind": "lint",
          "command": "npm run lint",
          "exitCode": 0,
          "passed": true,
          "afterModification": true
        }
      ],
      "failureRecovered": null
    },
    {
      "taskId": "M5",
      "createdAt": "2026-06-06T12:13:28.372+08:00",
      "complexity": "medium",
      "completedInFirstAttempt": true,
      "wrongFileModified": false,
      "unrelatedCodeChanged": false,
      "changedFiles": [
        "docs/superpowers/plans/2026-06-05-v0-2-stabilization.md"
      ],
      "validations": [
        {
          "kind": "typecheck",
          "command": "npm run typecheck",
          "exitCode": 0,
          "passed": true,
          "afterModification": true
        },
        {
          "kind": "build",
          "command": "npm run build",
          "exitCode": 0,
          "passed": true,
          "afterModification": true
        },
        {
          "kind": "lint",
          "command": "npm run lint",
          "exitCode": 0,
          "passed": true,
          "afterModification": true
        }
      ],
      "failureRecovered": null
    }
  ]
}
